Workbook
Name COMPANY_NAME: FrontPage!$A$1:$M$40
Name DETAIL: 'Detail Data'!$A$1:$G$40
Name FrontPage: FrontPage!$A$1:$G$40
Name FUNDAMENTALS: FrontPage!$H$2:$M$40
Name IQ_CH: 110000
Name IQ_CQ: 5000
Name IQ_CY: 10000
Name IQ_DAILY: 500000
Name IQ_FH: 100000
Name IQ_FQ: 500
Name IQ_FY: 1000
Name IQ_LTM: 2000
Name IQ_MONTH: 15000
Name IQ_NTM: 6000
Name IQ_WEEK: 50000
Name IQ_YTD: 3000

Sheet FrontPage
A2: Share Symbol: | E2: Exchange Traded: | H2: FUNDAMENTALS
A3: Recent price: (US$) | E3: Student: | H3: Most Recent Qtr Report | K3: Market Capitalization (M $$) | M3: =C3*'Detail Data'!E9 -> 0
A4: Date: | E4: TXST Email: | H4: Last Full Fiscal Year | K4: Enterprise Value (M $$) | M4: =M3+'Detail Data'!E34-'Detail Data'!E28 -> 0
C5: Index | E5: Earnings (GAAP) | F5: E (% Chg)-cagr | G5: Multiple | H5: Profitability | K5: Balance Sheet
A6: S&P 500 (t-1) | H6: Gross Margin (%) | I6: ='Detail Data'!E23 -> #DIV/0! | K6: Cash - M $$ | M6: ='Detail Data'!E28 -> 0
A7: S&P 500 (Current) | E7: =C7/C6-1 -> #DIV/0! | G7: =C7/F7 -> #DIV/0! | H7: Avg Gross Margin (3 yrs) | I7: =AVERAGE('Detail Data'!C23,'Detail Data'!D23,'Detail Data'!E23) -> #DIV/0! | K7: Cash per Share - $$ | M7: =M6/'Detail Data'!E9 -> #DIV/0!
A8: S&P 500 (t+1) | E8: =F8/F7-1 -> #DIV/0! | G8: =C8/F8 -> #DIV/0! | H8: Net Margin (%) | I8: ='Detail Data'!E25 -> #DIV/0! | K8: Free Cash Flow to the firm- M $$ | M8: ='Detail Data'!E41 -> #DIV/0!
A9: S&P 500 (t+2) | E9: =F9/F8-1 -> #DIV/0! | G9: =C9/F9 -> #DIV/0! | H9: Net Margin (3 Yrs) | I9: =AVERAGE('Detail Data'!C25,'Detail Data'!D25,'Detail Data'!E25) -> #DIV/0! | K9: FCFF per Share - SS | M9: =M8/'Detail Data'!E9 -> #DIV/0!
A10: Company Description | E10: CATALYSTS (RECENT DEVELOPMENTS) | H10: EBITDA Margin (%) | I10: ='Detail Data'!E26 -> #DIV/0! | K10: Net Debt - M $$ | M10: ='Detail Data'!E34 -> 0
E11: 1) 2) 3) | H11: Avg EBITDA Margin (%) | I11: =AVERAGE('Detail Data'!C26,'Detail Data'!D26,'Detail Data'!E26) -> #DIV/0! | K11: Net Debt/FCF - % | M11: =M10/M8 -> #DIV/0!
H12: Outlook | K12: Valuation Models | L12: Multiple | M12: Price Target
H13: Revenue Growth (LTM) | I13: =('Detail Data'!E5/'Detail Data'!D5)-1 -> #DIV/0! | K13: P/E (Current - LTM) | L13: ='Detail Data'!E12 -> #DIV/0! | M13: =L13*'Detail Data'!E7 -> #DIV/0!
H14: Revenue Growth (Fwd 12month) | I14: ='Detail Data'!F5/'Detail Data'!E5-1 -> #DIV/0! | K14: P/E (Fwd 12 Months) | L14: ='Detail Data'!F12 -> #DIV/0! | M14: =L13*'Detail Data'!F7 -> #DIV/0!
A15: Revenue Segments | E15: WHAT'S UNIQUE (MOAT) | H15: Revenue Growth (Fwd 24month) | I15: =(('Detail Data'!G5/'Detail Data'!E5)^(1/2))-1 -> #DIV/0! | K15: P/E (Fwd 24 Months) | L15: ='Detail Data'!G12 -> #DIV/0! | M15: =L13*'Detail Data'!G7 -> #DIV/0!
E16: 1) 2) | H16: EPS Growth (LTM) | I16: ='Detail Data'!E7/'Detail Data'!D7-1 -> #DIV/0! | K16: MC/Rev (Current - LTM) | L16: ='Detail Data'!E11 -> #DIV/0! | M16: =('Detail Data'!E11*'Detail Data'!E5)/'Detail Data'!E9 -> #DIV/0! | N16: Mult = (pr*sh)/rev
H17: EPS Growth (Fwd 12Month) | I17: ='Detail Data'!F7/'Detail Data'!E7-1 -> #DIV/0! | K17: MC/Rev (Fwd 12Month) | L17: ='Detail Data'!F11 -> #DIV/0! | M17: =('Detail Data'!E11*'Detail Data'!F5)/'Detail Data'!F9 -> #DIV/0! | N17: (Mult*Rev)/Sh
H18: EPS Growth (Fwd 24Month) | I18: =(('Detail Data'!G7/'Detail Data'!E7)^(1/2))-1 -> #DIV/0! | K18: MC/Rev (Fwd 24Month) | L18: ='Detail Data'!G11 -> #DIV/0! | M18: =('Detail Data'!E11*'Detail Data'!G5)/'Detail Data'!G9 -> #DIV/0! | N18: Mult = (EV / EBITDA)
A19: How Does the Company Make Money (Unit Economics)?? | E19: Main Strengths | H19: Capital Allocation | K19: EV / EBITDA (LTM) | L19: ='Detail Data'!E13 -> #DIV/0! | M19: =(('Detail Data'!E13*'Detail Data'!E21)-'Detail Data'!E34+'Detail Data'!E28)/'Detail Data'!E9 -> #DIV/0! | N19: Mult = (MC + Debt - Cash) / EBITDA
E20: 1) | H20: ROE | I20: ='Detail Data'!E35/AVERAGE('Detail Data'!E30,'Detail Data'!D30) -> #DIV/0! | K20: EV/EBITDA (Fwd 12Months) | L20: ='Detail Data'!F13 -> #DIV/0! | M20: =(('Detail Data'!E13*'Detail Data'!F21)+'Detail Data'!F28-'Detail Data'!F34)/'Detail Data'!F9 -> #DIV/0! | N20: Mult = ((Pr * SH)+ Debt - Cash) / EBITDA
E21: 2) | H21: Avg ROE (3 Yrs) | I21: ='Detail Data'!E17/AVERAGE('Detail Data'!C35,'Detail Data'!D35,'Detail Data'!E35) -> #DIV/0! | K21: EV/EBITDA (Fwd 24Months) | L21: ='Detail Data'!G13 -> #DIV/0! | M21: =(('Detail Data'!E13*'Detail Data'!G21)+'Detail Data'!G28-'Detail Data'!G34)/'Detail Data'!G9 -> #DIV/0! | N21: ((Mult*EBITDA)+Cash-Debt)/Sh
E22: 3) | H22: Asset Turnover | I22: ='Detail Data'!E40/AVERAGE('Detail Data'!E30,'Detail Data'!D30,'Detail Data'!C30) -> #DIV/0! | K22: EV / FCF (LTM) | L22: ='Detail Data'!E45 -> #DIV/0! | M22: =(('Detail Data'!E45*'Detail Data'!E41)+'Detail Data'!E28-'Detail Data'!E34)/'Detail Data'!E9 -> #DIV/0! | N22: Mult = EV / FCF
E23: Main Risks | H23: Avg AT (3 yrs) | I23: ='Detail Data'!E17/'Detail Data'!E35 -> #DIV/0! | K23: EV/FCF (Fwd 12Months) | L23: ='Detail Data'!F45 -> #DIV/0! | M23: =(('Detail Data'!E45*'Detail Data'!F41)+'Detail Data'!F28-'Detail Data'!F34)/'Detail Data'!F9 -> #DIV/0! | N23: Mult = ((Pr*sh)+Debt-Cash)/ FCF
A24: Main Peers / Comps | E24: 1) | H24: Fincl Lev | I24: =AVERAGE('Detail Data'!D30,'Detail Data'!E30)/AVERAGE('Detail Data'!D35,'Detail Data'!E35) -> #DIV/0! | K24: EV/FCF (Fwd 24Months) | L24: ='Detail Data'!G45 -> #DIV/0! | M24: =(('Detail Data'!E45*'Detail Data'!G41)+'Detail Data'!G28-'Detail Data'!G34)/'Detail Data'!G9 -> #DIV/0! | N24: Pr = ((Mult * FCF)+Cash-Debt) / Sh
A25: 1) | B25: 3) | E25: 2) | H25: Avg Fincl Lev (3 Yrs) | I25: =AVERAGE('Detail Data'!C30,'Detail Data'!D30,'Detail Data'!E30)/AVERAGE('Detail Data'!C35,'Detail Data'!D35,'Detail Data'!E35) -> #DIV/0!
A26: 2) | B26: 4) | E26: 3) | H26: FCF / NI (1 Yrs) | I26: ='Detail Data'!E41/'Detail Data'!E17 -> #DIV/0!
A27: Share Price (USD) - 5 yrs | H27: Avg FCF / NI (3 Yrs) | I27: =AVERAGE('Detail Data'!E41,'Detail Data'!D41,'Detail Data'!C41)/AVERAGE('Detail Data'!E17,'Detail Data'!D17,'Detail Data'!C17) -> #DIV/0!
H28: Capital Intensity | K28: Normalized Multiples
H29: CAPEX/Revenues - % | I29: ='Detail Data'!E40/'Detail Data'!E5 -> #DIV/0! | K29: (P/E) / EGr (Fwd 1Yr) - x | M29: ='Detail Data'!E12/(1+FrontPage!I16) -> #DIV/0!
H30: Avg CAPEX/Rev (3 yrs) - % | I30: =AVERAGE('Detail Data'!E40,'Detail Data'!D40,'Detail Data'!C40)/AVERAGE('Detail Data'!E5,'Detail Data'!D5,'Detail Data'!C5) -> #DIV/0! | K30: (MC/Rev) / RevGr (Fwd 1Yr) - x | M30: ='Detail Data'!E11/(1+FrontPage!I13) -> #DIV/0!
H31: CAPEX/Oper CF - % | I31: ='Detail Data'!E40/'Detail Data'!E44 -> #DIV/0! | K31: (EV/EBITDA) / EBITDA Gr (Fwd 1Yr) - x | M31: ='Detail Data'!E13/(('Detail Data'!E21/'Detail Data'!D21)) -> #DIV/0!
H32: Avg CAPEX/Oper CF (3 yrs) - % | I32: =AVERAGE('Detail Data'!E40,'Detail Data'!D40,'Detail Data'!C40)/AVERAGE('Detail Data'!E44,'Detail Data'!D44,'Detail Data'!C44) -> #DIV/0! | K32: (EV/FCF) / FCF Gr (Fwd 1Yr) - x | M32: ='Detail Data'!E45/(('Detail Data'!E41/'Detail Data'!D41)) -> #DIV/0!
H33: Share Summary
H34: Dividend ($ pSh): | K34: Short Interest (M Sh)
H35: Divd Yield: | I35: =I34/C3 -> #DIV/0! | K35: Short Interest (Month t-1) - (M Sh)
H36: Avg Daily Volumes (M Sh) | K36: Short Interest as % of Float - % | M36: =M34/I39 -> #DIV/0!
H37: Shares O/S (Basic) - (M Sh) | K37: Days to Cover | M37: =M34/I36 -> #DIV/0!
H38: Shares O/S (Fully Diluted) - (M Sh) | I38: ='Detail Data'!E9 -> 0 | K38: Number of Employees
H39: Float (M Sh) | K39: Rev per Employee - $$ | M39: =('Detail Data'!E5*1000000)/FrontPage!M38 -> #DIV/0!
H40: Institutional Ownership (%) | I40: =I39/I38 -> #DIV/0!
H44: 1) top | I44: 10 | K44: 0
H45: 2) Share Summary | I45: 9 | K45: 0
H46: 3) Boxes (5 each) | I46: =5*8 -> 40 | K46: 0
H47: 4) Pic | I47: 1 | K47: 0
H48: TOTAL | I48: =SUM(I44:I47) -> 60 | K48: =SUM(K44:K47) -> 0

Sheet Detail Data
A2: SUMMARY DATA (M$) | C2: =(YEAR(FrontPage!$C$4)-2)&"A" -> 1898A | D2: =YEAR(FrontPage!$C$4)-1&"A" -> 1899A | E2: =(YEAR(FrontPage!$C$4))&"F" -> 1900F | F2: =(YEAR(FrontPage!$C$4)+1)&"F" -> 1901F | G2: =(YEAR(FrontPage!$C$4)+2)&"F" -> 1902F
A3: Market Capitalization (M$) | C3: =C9*FrontPage!$C3 -> 0 | D3: =D9*FrontPage!C3 -> 0 | E3: =E9*FrontPage!C3 -> 0 | F3: =F9*FrontPage!C3 -> 0 | G3: =G9*FrontPage!C3 -> 0
A4: Enterprise Value (M$) | C4: =C3+C34-C28 -> 0 | D4: =D3+D34-D28 -> 0 | E4: =E3+E34-E28 -> 0 | F4: =F3+F34-F28 -> 0 | G4: =G3+G34-G28 -> 0
A5: =CONCATENATE("Revenue (t) - Current FY") -> Revenue (t) - Current FY
A6: =CONCATENATE("Revenue (t-1) - Previous FY") -> Revenue (t-1) - Previous FY | D6: =C5 -> 0 | E6: =D5 -> 0 | F6: =E5 -> 0 | G6: =F5 -> 0
A7: =CONCATENATE("FD EPS (t) - Current FY") -> FD EPS (t) - Current FY | C7: =C17/C9 -> #DIV/0! | D7: =D17/D9 -> #DIV/0! | E7: =E17/E9 -> #DIV/0! | F7: =F17/F9 -> #DIV/0! | G7: =G17/G9 -> #DIV/0!
A8: =CONCATENATE("FD EPS (t-1) - Previous FY") -> FD EPS (t-1) - Previous FY | C8: =C18/C9 -> #DIV/0! | D8: =C7 -> #DIV/0! | E8: =D7 -> #DIV/0! | F8: =E7 -> #DIV/0! | G8: =F7 -> #DIV/0!
A9: FD Shares outstanding (M) | D9: =C9 -> 0 | E9: =D9 -> 0 | F9: =E9 -> 0 | G9: =F9 -> 0
A10: VALUATION MULTIPLES | C10: =C2 -> 1898A | D10: =D2 -> 1899A | E10: =E2 -> 1900F | F10: =F2 -> 1901F | G10: =G2 -> 1902F
A11: Mkt Cap/Revenue | C11: =(FrontPage!$C3*C9)/C5 -> #DIV/0! | D11: =(FrontPage!C3*D9)/D5 -> #DIV/0! | E11: =E3/E5 -> #DIV/0! | F11: =F3/F5 -> #DIV/0! | G11: =G3/G5 -> #DIV/0!
A12: P/E | C12: =FrontPage!$C3/C7 -> #DIV/0! | D12: =FrontPage!C3/D7 -> #DIV/0! | E12: =FrontPage!C3/E7 -> #DIV/0! | F12: =FrontPage!$C3/F7 -> #DIV/0! | G12: =FrontPage!$C3/G7 -> #DIV/0!
A13: EV/EBITDA | C13: =$C4/C21 -> #DIV/0! | D13: =$C4/D21 -> #DIV/0! | E13: =$C4/E21 -> #DIV/0! | F13: =$C4/F21 -> #DIV/0! | G13: =$C4/G21 -> #DIV/0!
A14: INCOME STATEMENT (Millions $$) | C14: =C2 -> 1898A | D14: =D2 -> 1899A | E14: =E2 -> 1900F | F14: =F2 -> 1901F | G14: =G2 -> 1902F
A15: Cost of Sales
A16: EBIT (aka Pre-Tax Income / Oper Inc) | E16: =E21-E38 -> #DIV/0! | F16: =F21-F38 -> #DIV/0! | G16: =G21-G38 -> #DIV/0!
A17: Net Income (t) - Current FY
A18: =CONCATENATE("Net Income (t-1) - Previous FY") -> Net Income (t-1) - Previous FY | D18: =C17 -> 0 | E18: =D17 -> 0 | F18: =E17 -> 0 | G18: =F17 -> 0
A19: Interest Expense | E19: ='WACC calculation'!$C$13*'Detail Data'!E34 -> 0 | F19: ='WACC calculation'!$C$13*'Detail Data'!F34 -> 0 | G19: ='WACC calculation'!$C$13*'Detail Data'!G34 -> 0
A20: Income Taxes
A21: EBITDA | C21: =C16+C38 -> 0 | D21: =D16+D38 -> 0
A22: MARGINS (%) | C22: =C2 -> 1898A | D22: =D2 -> 1899A | E22: =E2 -> 1900F | F22: =F2 -> 1901F | G22: =G2 -> 1902F
A23: Gross Margin | C23: =(C5-C15)/C5 -> #DIV/0! | D23: =(D5-D15)/D5 -> #DIV/0! | E23: =(E5-E15)/E5 -> #DIV/0! | F23: =(F5-F15)/F5 -> #DIV/0! | G23: =(G5-G15)/G5 -> #DIV/0!
A24: EBIT Margin (aka Pre-Tax Margin) | C24: =C16/C5 -> #DIV/0! | D24: =D16/D5 -> #DIV/0! | E24: =E16/E5 -> #DIV/0! | F24: =F16/F5 -> #DIV/0! | G24: =G16/G5 -> #DIV/0!
A25: Net Income Margin (%) | C25: =C17/C5 -> #DIV/0! | D25: =D17/D5 -> #DIV/0! | E25: =E17/E5 -> #DIV/0! | F25: =F17/F5 -> #DIV/0! | G25: =G17/G5 -> #DIV/0!
A26: EBITDA Margin | C26: =C21/C5 -> #DIV/0! | D26: =D21/D5 -> #DIV/0! | E26: =E21/E5 -> #DIV/0! | F26: =F21/F5 -> #DIV/0! | G26: =G21/G5 -> #DIV/0!
A27: BALANCE SHEET (Millions $$) | C27: =C2 -> 1898A | D27: =D2 -> 1899A | E27: =E2 -> 1900F | F27: =F2 -> 1901F | G27: =G2 -> 1902F
A28: CASH & MKTBLE SECURITIES
A29: Cash & Mktble Sec per Share | C29: =C28/C9 -> #DIV/0! | D29: =D28/D9 -> #DIV/0! | E29: =E28/E9 -> #DIV/0! | F29: =F28/F9 -> #DIV/0! | G29: =G28/G9 -> #DIV/0!
A30: Total Assets
A31: Current Assets
A32: Current Liabilities
A33: Net Working Capital | C33: =C31-C32 -> 0 | D33: =D31-D32 -> 0 | E33: =E31-E32 -> 0 | F33: =F31-F32 -> 0 | G33: =G31-G32 -> 0
A34: Long Term Debt
A35: Equity
A36: CASH FLOW STATEMENT (Millions $$) | C36: =C2 -> 1898A | D36: =D2 -> 1899A | E36: =E2 -> 1900F | F36: =F2 -> 1901F | G36: =G2 -> 1902F
A37: NOPAT | C37: =C16*(1-C20/C17) -> #DIV/0! | D37: =D16*(1-D20/D17) -> #DIV/0! | E37: =E16*(1-E20/E17) -> #DIV/0! | F37: =F16*(1-F20/F17) -> #DIV/0! | G37: =G16*(1-G20/G17) -> #DIV/0!
A38: Depreciation + Amortization | E38: =D38/D40*E40 -> #DIV/0! | F38: =E38/E40*F40 -> #DIV/0! | G38: =F38/F40*G40 -> #DIV/0!
A39: Change in NWC | D39: =D33-C33 -> 0 | E39: =E33-D33 -> 0 | F39: =F33-E33 -> 0 | G39: =G33-F33 -> 0
A40: Capital Expenditures (PPE)
A41: Free Cash Flow to the Firm | B41: EBIT(1-t)+D&A-Capex-change in NWC | D41: =D37+D38-D39-D40 -> #DIV/0! | E41: =E37+E38-E39-E40 -> #DIV/0! | F41: =F37+F38-F39-F40 -> #DIV/0! | G41: =G37+G38-G39-G40 -> #DIV/0!
A42: Free Cash Flow to Equity | B42: FCFF - Interest(1-t) + Net Borrowings | D42: =D41-D19*(1-'DCF 1-Pager'!D25)+D34-C34 -> #DIV/0! | E42: =E41-E19*(1-'DCF 1-Pager'!E25)+E34-D34 -> #DIV/0! | F42: =F41-F19*(1-'DCF 1-Pager'!F25)+F34-E34 -> #DIV/0! | G42: =G41-G19*(1-'DCF 1-Pager'!G25)+G34-F34 -> #DIV/0!
A44: Cash from Operating Activities | E44: =E41+E40-E19*(1-'DCF 1-Pager'!E25) -> #DIV/0! | F44: =F41+F40-F19*(1-'DCF 1-Pager'!F25) -> #DIV/0! | G44: =G41+G40-G19*(1-'DCF 1-Pager'!G25) -> #DIV/0!
A45: EV/FCFF | D45: =D4/D41 -> #DIV/0! | E45: =E4/E41 -> #DIV/0! | F45: =F4/F41 -> #DIV/0! | G45: =G4/G41 -> #DIV/0!

Sheet DCF 1-Pager
B2: Discounted Cash Flow Valuation
B3: $ and shares in thousands, except for per share data
B4: Company name | D4: =FrontPage!A1 -> 0
B5: Ticker symbol | D5: =FrontPage!C2 -> 0
B6: Most recent fiscal year end | D6: 46022 | F6: Discount rate (WACC) | H6: ='WACC calculation'!C16 -> #DIV/0!
B7: End of first fiscal year | D7: =EOMONTH(D6,12) -> 46387 | F7: Share price (Public Co) | H7: =FrontPage!C3 -> 0
B8: Most recent quarter end date | D8: 46203 | F8: Share price date | H8: =D9 -> 0
B9: Valuation date | D9: =FrontPage!C4 -> 0 | F9: Midyear adjustment? | H9: 0
B10: Portion of year 1 cash flows in forecast | D10: =YEARFRAC(D9,D7) -> 127.00278
B12: Free cash flow to the firm (FCFF)
B13: Unlevered Free Cash Flows
D14: Actual | E14: Forecasts
B15: Fiscal year ended | D15: ='Detail Data'!D2 -> 1899A | E15: ='Detail Data'!E2 -> 1900F | F15: ='Detail Data'!F2 -> 1901F | G15: ='Detail Data'!G2 -> 1902F
B17: Revenue | D17: ='Detail Data'!D5 -> 0 | E17: ='Detail Data'!E5 -> 0 | F17: ='Detail Data'!F5 -> 0 | G17: ='Detail Data'!G5 -> 0
B18: % growth | E18: =E17/D17-1 -> #DIV/0! | F18: =F17/E17-1 -> #DIV/0! | G18: =G17/F17-1 -> #DIV/0!
B19: EBITDA | D19: ='Detail Data'!D21 -> 0 | E19: ='Detail Data'!E21 -> 0 | F19: ='Detail Data'!F21 -> 0 | G19: ='Detail Data'!G21 -> 0
B20: % margin | D20: =D19/D17 -> #DIV/0! | E20: =E19/E17 -> #DIV/0! | F20: =F19/F17 -> #DIV/0! | G20: =G19/G17 -> #DIV/0!
B21: EBIT | D21: ='Detail Data'!D16 -> 0 | E21: ='Detail Data'!E16 -> #DIV/0! | F21: ='Detail Data'!F16 -> #DIV/0! | G21: ='Detail Data'!G16 -> #DIV/0!
B22: % margin | D22: =D21/D17 -> #DIV/0! | E22: =E21/E17 -> #DIV/0! | F22: =F21/F17 -> #DIV/0! | G22: =G21/G17 -> #DIV/0!
B24: Tax on EBIT | D24: =D25*D21 -> #DIV/0! | E24: =E25*E21 -> #DIV/0! | F24: =F25*F21 -> #DIV/0! | G24: =G25*G21 -> #DIV/0!
B25: Tax rate | D25: ='Detail Data'!D20/'Detail Data'!D17 -> #DIV/0! | E25: ='Detail Data'!E20/'Detail Data'!E17 -> #DIV/0! | F25: ='Detail Data'!F20/'Detail Data'!F17 -> #DIV/0! | G25: ='Detail Data'!G20/'Detail Data'!G17 -> #DIV/0!
B26: NOPAT (aka EBIAT) | D26: =D21-D24 -> #DIV/0! | E26: =E21-E24 -> #DIV/0! | F26: =F21-F24 -> #DIV/0! | G26: =G21-G24 -> #DIV/0!
B28: Depreciation & amortization | D28: =D19-D21 -> 0 | E28: =E19-E21 -> #DIV/0! | F28: =F19-F21 -> #DIV/0! | G28: =G19-G21 -> #DIV/0!
B29: Changes in net working capital | D29: =C36-D36 -> 0 | E29: =D36-E36 -> 0 | F29: =E36-F36 -> 0 | G29: =F36-G36 -> 0
B30: Capital expenditures | D30: =-'Detail Data'!D40 -> 0 | E30: =-'Detail Data'!E40 -> 0 | F30: =-'Detail Data'!F40 -> 0 | G30: =-'Detail Data'!G40 -> 0
B31: as % of revenue | D31: =FrontPage!I30 -> #DIV/0! | E31: =D31 -> #DIV/0! | F31: =E31 -> #DIV/0! | G31: =F31 -> #DIV/0!
B33: Free cash flow to the firm
B34: Unlevered free cash flows (UFCF)
B36: Net working capital (WC Assets - WC liabilities) | C36: ='Detail Data'!C33 -> 0 | D36: ='Detail Data'!D33 -> 0 | E36: ='Detail Data'!E33 -> 0 | F36: ='Detail Data'!F33 -> 0 | G36: ='Detail Data'!G33 -> 0
B37: as % of revenue | D37: =D36/D17 -> #DIV/0! | E37: =E36/E17 -> #DIV/0! | F37: =F36/F17 -> #DIV/0! | G37: =G36/G17 -> #DIV/0!
B39: ="Present value of UFCF on "&TEXT(D9,"mmm dd, yyyy")&" valuation date" -> Present value of UFCF on Jan 00, 1900 valuation date
D40: Val date | E40: Yr 1 - Stub | F40: Year 2 | G40: Year 3
B41: Date for discounting cash flows | D41: =D9 -> 0 | E41: =DATE(YEAR($D$6)+1,12,31) -> 46387 | F41: =DATE(YEAR($D$6)+2,12,31) -> 46752 | G41: =DATE(YEAR($D$6)+3,12,31) -> 47118
B42: Unlevered free cash flows (UFCF) stub adjusted | C42: =D10 -> 127.00278 | E42: =(E26+E28+E29+E30)*C42 -> #DIV/0! | F42: =F26+F28+F29+F30 -> #DIV/0! | G42: =G26+G28+G29+G30 -> #DIV/0! | K42: <-Stub year counts first year cash flows starting at the valuation date
B43: Present value of of unlevered free cash flows | E43: =E42/(1+$H$6)^((E41-$D$41)/365) -> #DIV/0! | F43: =F42/(1+$H$6)^((F41-$D$41)/365) -> #DIV/0! | G43: =G42/(1+$H$6)^((G41-$D$41)/365) -> #DIV/0!
B45: Terminal value - growth in perpetuity approach | E45: Terminal value - EBITDA multiple approach
B46: Long term growth rate | C46: 0.03 | E46: Terminal year EBITDA | I46: =G19 -> 0
B47: =YEAR(G41)&" FCF x (1+g)" -> 2028 FCF x (1+g) | C47: =G42*(1+C46) -> #DIV/0! | E47: EBITDA multiple | I47: 13.5
B48: ="Terminal value in "&YEAR(D6)+3 -> Terminal value in 2028 | C48: =C47/(H6-C46) -> #DIV/0! | E48: ="Terminal value in "&YEAR(G41) -> Terminal value in 2028 | I48: =I46*I47 -> 0
B49: Present value of terminal value | C49: =C48/(1+$H$6)^(($G$41-$D$41)/365) -> #DIV/0! | E49: Present value of terminal value | I49: =I48/(1+$H$6)^(($G$41-$D$41)/365) -> #DIV/0!
B50: Present value of stage 1 cash flows | C50: =SUM(E43:G43) -> #DIV/0! | E50: Present value of stage 1 cash flows | I50: =SUM(E43:I43) -> #DIV/0!
B51: Total enterprise value (TEV) | C51: =C49+C50 -> #DIV/0! | E51: Enterprise value (stage 1 + 2) | I51: =I49+I50 -> #DIV/0!
B53: Terminal value as % of TEV | C53: =C49/$C$51 -> #DIV/0! | E53: Terminal value as % of TEV | I53: =I49/$I$51 -> #DIV/0!
B54: Stage 1 cash flows as % of TEV | C54: =C50/$C$51 -> #DIV/0! | E54: Stage 1 cash flows as % of TEV | I54: =I50/$I$51 -> #DIV/0!
B55: Implied TV exit EBITDA multiple | C55: =C48/G19 -> #DIV/0! | E55: Implied terminal growth rate | I55: =(H6-G42/I48)/(1+G42/I48) -> #DIV/0!
B57: Net debt | E57: Shares outstanding
B58: Source doc | C58: Factset
B59: Source date | C59: 46022 | G59: Source doc | H59: Date | I59: Shares
B60: Gross debt and equivalents | E60: Basic shares | G60: Q1 2020 10Q | H60: 43847 | I60: =145628.076+59613.777 -> 205241.85
B61: Debt | C61: ='Detail Data'!D34 -> 0 | E61: Restricted stock / RSUs | G61: Q1 2020 10Q | H61: 43827 | I61: 1303.521
B62: Convertible debt | C62: 0 | E62: Options / warrants | I62: 609 | K62: <-These are options issued by the company, like to executives
B63: Preferred stock | C63: 0 | E63: Convertible debt | I63: 0 | K63: <-Look on FINRA for this if you can't find it in the 10-K
B64: Noncontrolling (minority) interests | C64: 0 | E64: Convertible preferred stock | I64: 0 | K64: <-Very few companies have this
B65: Nonoperating assets | E65: Net diluted shares outstanding | I65: =SUM(I60:I64) -> 207154.37
B66: Cash | C66: ='Detail Data'!D28 -> 0
B67: Equity investments | C67: 0
B69: Net debt | C69: =SUM(C61:C64)-SUM(C66:C67) -> 0
B71: Valuation
C72: Perpetuity | D72: EBITDA
B73: Enterprise value | C73: =C51 -> #DIV/0! | D73: =I51 -> #DIV/0!
B74: Net debt | C74: =C69 -> 0 | D74: =C74 -> 0
B75: Equity value | C75: =C73-C74 -> #DIV/0! | D75: =D73-D74 -> #DIV/0!
B76: Shares outstanding | C76: 205306 | D76: =C76 -> 205306
B77: Equity value per share | C77: =C75/C76 -> #DIV/0! | D77: =D75/D76 -> #DIV/0!
B79: Year 1 Multiples | C79: Perpetuity | D79: EBITDA
B80: EV / Revenue | C80: =C73/$E$17 -> #DIV/0! | D80: =D73/$E$17 -> #DIV/0!
B81: EV / EBITDA | C81: =C73/$E$19 -> #DIV/0! | D81: =D73/$E$19 -> #DIV/0!
B82: EV / EBIT | C82: =C73/$E$21 -> #DIV/0! | D82: =D73/$E$21 -> #DIV/0!
B85: Free cash flow to equity
B86: ="Present value of UFCF on "&TEXT(D9,"mmm dd, yyyy")&" valuation date" -> Present value of UFCF on Jan 00, 1900 valuation date
D87: Val date | E87: Yr 1 - Stub | F87: Year 2 | G87: Year 3
B88: Date for discounting cash flows | D88: =D9 -> 0 | E88: =DATE(YEAR($D$6)+1,12,31) -> 46387 | F88: =DATE(YEAR($D$6)+2,12,31) -> 46752 | G88: =DATE(YEAR($D$6)+3,12,31) -> 47118
B89: Unlevered free cash flows (UFCF) stub adjusted | C89: =C42 -> 127.00278 | E89: =C89*'Detail Data'!D42 -> #DIV/0! | F89: ='Detail Data'!E42 -> #DIV/0! | G89: ='Detail Data'!F42 -> #DIV/0!
B90: Present value of of unlevered free cash flows | E90: =E89/(1+'WACC calculation'!$C$11)^((E88-$D$41)/365) -> #DIV/0! | F90: =F89/(1+'WACC calculation'!$C$11)^((F88-$D$41)/365) -> #DIV/0! | G90: =G89/(1+'WACC calculation'!$C$11)^((G88-$D$41)/365) -> #DIV/0!
B92: Terminal value - growth in perpetuity approach | E92: Terminal value - PE multiple approach
B93: Long term growth rate | C93: 0.03 | E93: Terminal year Earnings | I93: =G26 -> #DIV/0!
B94: =YEAR(G88)&" FCF x (1+g)" -> 2028 FCF x (1+g) | C94: =G89*(1+C93) -> #DIV/0! | E94: EBITDA multiple | I94: 25.3
B95: ="Terminal value in "&YEAR(G88) -> Terminal value in 2028 | C95: =C94/('WACC calculation'!C11-C93) -> #DIV/0! | E95: ="Terminal value in "&YEAR(G88) -> Terminal value in 2028 | I95: =I93*I94 -> #DIV/0!
B96: Present value of terminal value | C96: =C95/(1+$H$6)^(($G$41-$D$41)/365) -> #DIV/0! | E96: Present value of terminal value | I96: =I95/(1+'WACC calculation'!C11)^(($G$41-$D$41)/365) -> #DIV/0!
B97: Present value of stage 1 cash flows | C97: =SUM(E90:G90) -> #DIV/0! | E97: Present value of stage 1 cash flows | I97: =SUM(E90:I90) -> #DIV/0!
B98: Total equity value (TEV) | C98: =C96+C97 -> #DIV/0! | E98: Equity Value | I98: =I96+I97 -> #DIV/0!
B100: Terminal value as % of TEV | C100: =C96/$C$51 -> #DIV/0! | E100: Terminal value as % of TEV | I100: =I96/$I$51 -> #DIV/0!
B101: Stage 1 cash flows as % of TEV | C101: =C97/$C$51 -> #DIV/0! | E101: Stage 1 cash flows as % of TEV | I101: =I97/$I$51 -> #DIV/0!
B102: Implied TV exit EBITDA multiple | C102: =C95/G89 -> #DIV/0! | E102: Implied terminal growth rate | I102: =(H54-G89/I95)/(1+G89/I95) -> #DIV/0!
B104: Valuation
C105: Perpetuity | D105: PE
B106: Equity value | C106: =C98 -> #DIV/0! | D106: =I98 -> #DIV/0!
B107: Shares outstanding | C107: 205306 | D107: =C107 -> 205306
B108: Equity value per share | C108: =C106/C107 -> #DIV/0! | D108: =D106/D107 -> #DIV/0!
B110: Outputs
D112: Equity value per share | L112: Year 1 EBITDA multiple
E113: Long term growth rate (g): | M113: Long term growth rate (g):
D114: =C77 -> #DIV/0! | E114: =F114-0.005 -> 0.02 | F114: =G114-0.005 -> 0.025 | G114: 0.03 | H114: =G114+0.005 -> 0.035 | I114: =H114+0.005 -> 0.04 | L114: =C81 -> #DIV/0! | M114: =N114-0.005 -> 0.02 | N114: =O114-0.005 -> 0.025 | O114: 0.03 | P114: =O114+0.005 -> 0.035 | Q114: =P114+0.005 -> 0.04
D115: =D116+0.005 -> 0.1 | E115: #DIV/0! | F115: #DIV/0! | G115: #DIV/0! | H115: #DIV/0! | I115: #DIV/0! | L115: =L116+0.005 -> 0.1 | M115: #DIV/0! | N115: #DIV/0! | O115: #DIV/0! | P115: #DIV/0! | Q115: #DIV/0!
D116: =D117+0.005 -> 0.095 | E116: #DIV/0! | F116: #DIV/0! | G116: #DIV/0! | H116: #DIV/0! | I116: #DIV/0! | L116: =L117+0.005 -> 0.095 | M116: #DIV/0! | N116: #DIV/0! | O116: #DIV/0! | P116: #DIV/0! | Q116: #DIV/0!
C117: WACC: | D117: 0.09 | E117: #DIV/0! | F117: #DIV/0! | G117: #DIV/0! | H117: #DIV/0! | I117: #DIV/0! | K117: WACC: | L117: 0.09 | M117: #DIV/0! | N117: #DIV/0! | O117: #DIV/0! | P117: #DIV/0! | Q117: #DIV/0!
D118: =D117-0.005 -> 0.085 | E118: #DIV/0! | F118: #DIV/0! | G118: #DIV/0! | H118: #DIV/0! | I118: #DIV/0! | L118: =L117-0.005 -> 0.085 | M118: #DIV/0! | N118: #DIV/0! | O118: #DIV/0! | P118: #DIV/0! | Q118: #DIV/0!
B119: Data | D119: =D118-0.005 -> 0.08 | E119: #DIV/0! | F119: #DIV/0! | G119: #DIV/0! | H119: #DIV/0! | I119: #DIV/0! | L119: =L118-0.005 -> 0.08 | M119: #DIV/0! | N119: #DIV/0! | O119: #DIV/0! | P119: #DIV/0! | Q119: #DIV/0!
B120: Tables
D121: Equity value per share | L121: Year 1 EBITDA multiple
...

Sheet WACC calculation
D2: weight
B3: Market Value of Equity | C3: ='Detail Data'!D3 -> 0 | D3: =C3/C5 -> #DIV/0!
B4: Book Value of Debt | C4: ='Detail Data'!D34 -> 0 | D4: =C4/C5 -> #DIV/0!
B5: Total Market Value (EV) | C5: =C3+C4 -> 0
B7: Cost of Equity:
B8: Rm - Rf (Market Risk Premium) | C8: 0.0442
B9: Rf | C9: 0.0496 | D9: FRED DGS10, 10-year Treasury, 2026-09-11
B10: Beta | C10: 0.35
B11: Cost of Equity | C11: =C9+C10*C8 -> 0.06507
B13: Cost of Debt | C13: 0.0557 | D13: FRED BAMLC0A3CAEY, ICE BofA single-A corporate effective yield, 2026-09-11 (Hershey is rated A)
B14: Tax rate | C14: ='DCF 1-Pager'!D25 -> #DIV/0!
B16: WACC | C16: =D3*C11+D4*C13*(1-C14) -> #DIV/0!

Sheet Key Defns
D1: The score is calculated based on 9 criteria divided into 3 groups.[1]
A2: PE (Curr) = | B2: ='Detail Data'!E12 -> #DIV/0! | D2: Profitability
A3: F (26) EPS = | B3: ='Detail Data'!G7 -> #DIV/0! | D3: 1. Return on Assets (1 point if it is positive in the current year, 0 otherwise);
A4: F( Price Stock) | B4: =B2*B3 -> #DIV/0! | D4: 2. Operating Cash Flow (1 point if it is positive in the current year, 0 otherwise);
A8: Gain | B8: =B4/#REF!-1 -> #DIV/0! | D8: 4. Accruals (1 point if Operating Cash Flow/Total Assets is higher than ROA in the current year, 0 otherwise);
D9: Leverage, Liquidity and Source of Funds
A10: MC/Rev (Curr) | B10: ='Detail Data'!E11 -> #DIV/0! | D10: 5. Change in Leverage (long-term) ratio (1 point if the ratio is lower this year compared to the previous one, 0 otherwise);
A11: MC (Current) | B11: ='Detail Data'!E3 -> 0 | D11: 6. Change in Current ratio (1 point if it is higher in the current year compared to the previous one, 0 otherwise);
A12: E (MC Curr Mult) | B12: ='Detail Data'!G5*'Detail Data'!E11 -> #DIV/0! | D12: 7. Change in the number of shares (1 point if no new shares were issued during the last year);
A13: Shares | B13: ='Detail Data'!E9 -> 0 | D13: Operating Efficiency
A14: Price | B14: =B11/B13 -> #DIV/0! | D14: 8. Change in Gross Margin (1 point if it is higher in the current year compared to the previous one, 0 otherwise);
A15: Gain | B15: =B14/#REF!-1 -> #DIV/0! | D15: 9. Change in Asset Turnover ratio (1 point if it is higher in the current year compared to the previous one, 0 otherwise);
D17: The score is calculated based on the data from financial statement of a company. A company gets 1 point for each met criteria. Summing up of all achieved points gives Piotroski F-score (number between 0 and 9).
D18: https://www.chicagobooth.edu/~/media/FE874EE65F624AAEBD0166B1974FD74D.pdf
A19: ='Detail Data'!#REF!-'Detail Data'!#REF! -> #REF! | D19: Improvements to Piotrowski F-Score
A20: ='Detail Data'!#REF!-'Detail Data'!#REF! -> #REF! | D20: https://alphaarchitect.com/2015/05/05/value-investing-research-simple-methods-to-improve-the-piotroski-f-score/
D21: https://www.aaii.com/journal/article/simple-methods-to-improve-the-piotroski-f-score?
A22: https://www.goldmansachs.com/insights/articles/the-s-and-p-500-is-forecast-to-return-10-percent-in-2025
A23: https://www.goldmansachs.com/insights/articles/s-and-p-500-projected-to-rally-more-than-expected
D25: GLOSSARY AND INTERPRETATION OF FIGURES
D28: Adjusted book value | G28: An estimate of the book value of the company, using the sum of capital expenditures for the
G29: last 5 years as an estimate for the book value of fixed assets, to determine how new
G30: such fixed assets are, and how strong the book value.
D36: SHORT INTEREST | F36: https://www.nasdaq.com/market-activity/stocks/msft/short-interest
D37: NYSE : Short Interest | F37: https://www.nyse.com/quote/XNGS:MSFT
D38: Institutional Ownership | F38: https://www.nasdaq.com/market-activity/stocks/exas/institutional-holdings
D40: Definitions
D43: Adjusted sales/share | G43: Sales per share, where the number of shares is adjusted for shares which could be repurchased
G44: with excess current assets, once all outstanding liabilities have been extinguished.
G45: Accounts for the leverage of the company (how many shares would need to be issued to retire
G46: the debt) or, conversely, for the benefits from high levels of net assets.
G47: Especially valuable for inter-company comparisons, or comparison to industry average.
D48: Asset value | G48: An estimate of the fair value of tangible assets, net of all outstanding liabilities.
G49: Fixed assets include accumulated depreciation, to estimate their replacement value.
G51: When real estate represents a significant portion of assets, an adjustment may be made
G52: to reflect its fair market value rather than book value.
G53: An estimate is also made for goodwill, as a % of revenues.
D55: Cap.Ex. | G55: Capital expenditures relating to fixed asset purchases.
D57: CFO | G57: Cash flow from operations (including changes in non-cash working capital accounts).
D59: EBIT | G59: Earnings before interest and taxes.
D60: EBIT Multiple | G60: An estimate of the earnings generation powers of the company's productive assets, plus
G61: working capital, and netted of long term debt outstanding.
G62: The lower the EBIT multiple, the greater the probability that the stock is undervalued at current
G63: market levels. On average, a multiple greater than 5.0 indicates possible overvaluation.
G64: This multiple is also useful for inter-company comparisons, as it accounts for the effect of
G65: varying levels of leverage and differing income tax rates.
D67: F score | G67: A rapid evaluation of financial strength, reflecting the liquidity of the company and its
G68: leverage position, also relating the two.
G69: The higher, the better.
D71: NBP | G71: An estimate of the remaining borrowing power of the Company, based on the level of its
D72: Net borrowing power | G72: short term and gross fixed assets, over and above debt already outstanding.

Sheet Sheet1
